email_to/__init__.py
email_to/email_to.py
email_to-0.1.0.dist-info/DESCRIPTION.rst
email_to-0.1.0.dist-info/METADATA
email_to-0.1.0.dist-info/RECORD
email_to-0.1.0.dist-info/WHEEL
email_to-0.1.0.dist-info/metadata.json
email_to-0.1.0.dist-info/top_level.txt
