Metadata-Version: 1.1
Name: email-to
Version: 0.1.0
Summary: Simplyify sending HTML emails
Home-page: https://github.com/abkfenris/email_to
Author: Alex Kerney
Author-email: abk@mac.com
License: MIT license
Keywords: email_to
Platform: UNKNOWN
Classifier: Development Status :: 2 - Pre-Alpha
Classifier: Intended Audience :: Developers
Classifier: License :: OSI Approved :: MIT License
Classifier: Natural Language :: English
Classifier: Programming Language :: Python :: 2
Classifier: Programming Language :: Python :: 2.6
Classifier: Programming Language :: Python :: 2.7
Classifier: Programming Language :: Python :: 3
Classifier: Programming Language :: Python :: 3.3
Classifier: Programming Language :: Python :: 3.4
Classifier: Programming Language :: Python :: 3.5
